prop/__init__.py
prop/algorithms/__init__.py
prop/algorithms/a2c.py
prop/algorithms/dqn.py
prop/buffers/__init__.py
prop/buffers/panic_buffer.py
prop/buffers/priority_replay_buffer.py
prop/buffers/replay_buffer.py
prop/net/__init__.py
prop/net/feed_forward.py
rlprop-0.0.4.dist-info/LICENSE
rlprop-0.0.4.dist-info/METADATA
rlprop-0.0.4.dist-info/WHEEL
rlprop-0.0.4.dist-info/top_level.txt
rlprop-0.0.4.dist-info/RECORD
