Metadata-Version: 2.1
Name: rlprop
Version: 0.0.4
Summary: Reinforcement Learning agents implemented in pytorch
Home-page: https://github.com/abstractpaper/prop
Author: Aziz Alfoudari
Author-email: aziz.alfoudari@gmail.com
License: UNKNOWN
Platform: UNKNOWN
Classifier: Programming Language :: Python :: 3
Classifier: License :: OSI Approved :: MIT License
Classifier: Operating System :: OS Independent
Requires-Python: >=3.6
Requires-Dist: numpy
Requires-Dist: gym
Requires-Dist: torch
Requires-Dist: tensorboardX
